marshmallow_validators/__init__.py
marshmallow_validators/colander.py
marshmallow_validators/core.py
marshmallow_validators/wtforms.py
marshmallow_validators-3.0.0.dist-info/METADATA
marshmallow_validators-3.0.0.dist-info/RECORD
marshmallow_validators-3.0.0.dist-info/WHEEL
marshmallow_validators-3.0.0.dist-info/top_level.txt
