Metadata-Version: 2.1
Name: marshmallow-validators
Version: 3.0.0
Summary: Use 3rd-party validators (e.g. from WTForms and colander) with marshmallow
Home-page: https://github.com/marshmallow-code/marshmallow-validators
Author: Steven Loria
Author-email: sloria1@gmail.com
License: MIT
Keywords: validators marshmallow
Platform: UNKNOWN
Classifier: Intended Audience :: Developers
Classifier: License :: OSI Approved :: MIT License
Classifier: Natural Language :: English
Classifier: Programming Language :: Python :: 2
Classifier: Programming Language :: Python :: 2.7
Classifier: Programming Language :: Python :: 3
Classifier: Programming Language :: Python :: 3.4
Classifier: Programming Language :: Python :: 3.5
Classifier: Programming Language :: Python :: 3.6
Requires-Dist: marshmallow (>=2.0.0b4)
